[
  {
    "model":"base",
    "test_season":2007,
    "train_until":2006,
    "n_bets_model":380,
    "roi_model":-0.0354473684,
    "profit_model":-13.47,
    "hit_rate":0.5,
    "avg_odds":2.0327631579,
    "avg_edge":0.0058767546,
    "avg_value_ev":0.0766440043,
    "max_drawdown_pct":3.5943600868,
    "stake_m":1.0,
    "min_edge":0.0,
    "investment_total_model":380.0,
    "acc":0.5078947368,
    "logloss":1.0105398298,
    "brier":0.6026234795,
    "roi_bet365":-0.0347105263,
    "profit_bet365":-13.19,
    "investment_total":380.0,
    "n_bets_bet365":380,
    "stake_b":1.0,
    "investment_total_bet365":380.0,
    "delta_roi":-0.0007368421,
    "delta_profit":-0.28
  },
  {
    "model":"base",
    "test_season":2008,
    "train_until":2007,
    "n_bets_model":380,
    "roi_model":0.1037105263,
    "profit_model":39.41,
    "hit_rate":0.5763157895,
    "avg_odds":1.9917368421,
    "avg_edge":0.0148631343,
    "avg_value_ev":0.0881030712,
    "max_drawdown_pct":0.7037370554,
    "stake_m":1.0,
    "min_edge":0.0,
    "investment_total_model":380.0,
    "acc":0.5710526316,
    "logloss":0.970600456,
    "brier":0.5735880526,
    "roi_bet365":0.0790789474,
    "profit_bet365":30.05,
    "investment_total":380.0,
    "n_bets_bet365":380,
    "stake_b":1.0,
    "investment_total_bet365":380.0,
    "delta_roi":0.0246315789,
    "delta_profit":9.36
  },
  {
    "model":"base",
    "test_season":2009,
    "train_until":2008,
    "n_bets_model":380,
    "roi_model":0.0114473684,
    "profit_model":4.35,
    "hit_rate":0.5631578947,
    "avg_odds":1.9332894737,
    "avg_edge":0.0053097003,
    "avg_value_ev":0.0868948911,
    "max_drawdown_pct":0.9879081016,
    "stake_m":1.0,
    "min_edge":0.0,
    "investment_total_model":380.0,
    "acc":0.5815789474,
    "logloss":0.9213542305,
    "brier":0.5470738005,
    "roi_bet365":0.0428421053,
    "profit_bet365":16.28,
    "investment_total":380.0,
    "n_bets_bet365":380,
    "stake_b":1.0,
    "investment_total_bet365":380.0,
    "delta_roi":-0.0313947368,
    "delta_profit":-11.93
  },
  {
    "model":"base",
    "test_season":2010,
    "train_until":2009,
    "n_bets_model":380,
    "roi_model":0.1329473684,
    "profit_model":50.52,
    "hit_rate":0.6210526316,
    "avg_odds":1.8902894737,
    "avg_edge":-0.0075532459,
    "avg_value_ev":0.073829881,
    "max_drawdown_pct":0.2495427228,
    "stake_m":1.0,
    "min_edge":0.0,
    "investment_total_model":380.0,
    "acc":0.6078947368,
    "logloss":0.9292281321,
    "brier":0.5457396657,
    "roi_bet365":0.0904210526,
    "profit_bet365":34.36,
    "investment_total":380.0,
    "n_bets_bet365":380,
    "stake_b":1.0,
    "investment_total_bet365":380.0,
    "delta_roi":0.0425263158,
    "delta_profit":16.16
  },
  {
    "model":"base",
    "test_season":2011,
    "train_until":2010,
    "n_bets_model":380,
    "roi_model":-0.0153684211,
    "profit_model":-5.84,
    "hit_rate":0.5578947368,
    "avg_odds":1.8751052632,
    "avg_edge":-0.0049791748,
    "avg_value_ev":0.0691969255,
    "max_drawdown_pct":2.980733945,
    "stake_m":1.0,
    "min_edge":0.0,
    "investment_total_model":380.0,
    "acc":0.5368421053,
    "logloss":0.9467655454,
    "brier":0.5631493981,
    "roi_bet365":-0.0791052632,
    "profit_bet365":-30.06,
    "investment_total":380.0,
    "n_bets_bet365":380,
    "stake_b":1.0,
    "investment_total_bet365":380.0,
    "delta_roi":0.0637368421,
    "delta_profit":24.22
  },
  {
    "model":"base",
    "test_season":2012,
    "train_until":2011,
    "n_bets_model":380,
    "roi_model":-0.0403157895,
    "profit_model":-15.32,
    "hit_rate":0.55,
    "avg_odds":1.8775263158,
    "avg_edge":0.0062390932,
    "avg_value_ev":0.0737646511,
    "max_drawdown_pct":3.0972364381,
    "stake_m":1.0,
    "min_edge":0.0,
    "investment_total_model":380.0,
    "acc":0.5526315789,
    "logloss":0.9428215745,
    "brier":0.5565938014,
    "roi_bet365":-0.0373684211,
    "profit_bet365":-14.2,
    "investment_total":380.0,
    "n_bets_bet365":380,
    "stake_b":1.0,
    "investment_total_bet365":380.0,
    "delta_roi":-0.0029473684,
    "delta_profit":-1.12
  },
  {
    "model":"base",
    "test_season":2013,
    "train_until":2012,
    "n_bets_model":380,
    "roi_model":-0.0591052632,
    "profit_model":-22.46,
    "hit_rate":0.5447368421,
    "avg_odds":1.8659736842,
    "avg_edge":0.0126959619,
    "avg_value_ev":0.0920786425,
    "max_drawdown_pct":4.6836419753,
    "stake_m":1.0,
    "min_edge":0.0,
    "investment_total_model":380.0,
    "acc":0.5368421053,
    "logloss":0.9556050889,
    "brier":0.5648192688,
    "roi_bet365":-0.0991052632,
    "profit_bet365":-37.66,
    "investment_total":380.0,
    "n_bets_bet365":380,
    "stake_b":1.0,
    "investment_total_bet365":380.0,
    "delta_roi":0.04,
    "delta_profit":15.2
  },
  {
    "model":"base",
    "test_season":2014,
    "train_until":2013,
    "n_bets_model":380,
    "roi_model":-0.0051315789,
    "profit_model":-1.95,
    "hit_rate":0.5789473684,
    "avg_odds":1.8556842105,
    "avg_edge":-0.0066642497,
    "avg_value_ev":0.071464857,
    "max_drawdown_pct":15.3,
    "stake_m":1.0,
    "min_edge":0.0,
    "investment_total_model":380.0,
    "acc":0.5657894737,
    "logloss":0.902423833,
    "brier":0.5300615058,
    "roi_bet365":-0.0601052632,
    "profit_bet365":-22.84,
    "investment_total":380.0,
    "n_bets_bet365":380,
    "stake_b":1.0,
    "investment_total_bet365":380.0,
    "delta_roi":0.0549736842,
    "delta_profit":20.89
  },
  {
    "model":"base",
    "test_season":2015,
    "train_until":2014,
    "n_bets_model":380,
    "roi_model":-0.0189736842,
    "profit_model":-7.21,
    "hit_rate":0.5578947368,
    "avg_odds":1.8978421053,
    "avg_edge":-0.01116194,
    "avg_value_ev":0.0753263905,
    "max_drawdown_pct":7.375,
    "stake_m":1.0,
    "min_edge":0.0,
    "investment_total_model":380.0,
    "acc":0.5473684211,
    "logloss":0.92942685,
    "brier":0.5507083193,
    "roi_bet365":-0.0625789474,
    "profit_bet365":-23.78,
    "investment_total":380.0,
    "n_bets_bet365":380,
    "stake_b":1.0,
    "investment_total_bet365":380.0,
    "delta_roi":0.0436052632,
    "delta_profit":16.57
  },
  {
    "model":"base",
    "test_season":2016,
    "train_until":2015,
    "n_bets_model":380,
    "roi_model":0.0593947368,
    "profit_model":22.57,
    "hit_rate":0.6026315789,
    "avg_odds":1.8685,
    "avg_edge":-0.0027212296,
    "avg_value_ev":0.0844992437,
    "max_drawdown_pct":0.4830659537,
    "stake_m":1.0,
    "min_edge":0.0,
    "investment_total_model":380.0,
    "acc":0.5868421053,
    "logloss":0.9026510018,
    "brier":0.5319314022,
    "roi_bet365":0.0005789474,
    "profit_bet365":0.22,
    "investment_total":380.0,
    "n_bets_bet365":380,
    "stake_b":1.0,
    "investment_total_bet365":380.0,
    "delta_roi":0.0588157895,
    "delta_profit":22.35
  },
  {
    "model":"base",
    "test_season":2017,
    "train_until":2016,
    "n_bets_model":380,
    "roi_model":0.0713157895,
    "profit_model":27.1,
    "hit_rate":0.5763157895,
    "avg_odds":1.9346315789,
    "avg_edge":-0.0155391484,
    "avg_value_ev":0.0778615057,
    "max_drawdown_pct":0.6360818351,
    "stake_m":1.0,
    "min_edge":0.0,
    "investment_total_model":380.0,
    "acc":0.55,
    "logloss":0.9595552614,
    "brier":0.5705010744,
    "roi_bet365":-0.0286842105,
    "profit_bet365":-10.9,
    "investment_total":380.0,
    "n_bets_bet365":380,
    "stake_b":1.0,
    "investment_total_bet365":380.0,
    "delta_roi":0.1,
    "delta_profit":38.0
  },
  {
    "model":"base",
    "test_season":2018,
    "train_until":2017,
    "n_bets_model":380,
    "roi_model":-0.0935,
    "profit_model":-35.53,
    "hit_rate":0.4947368421,
    "avg_odds":1.9553684211,
    "avg_edge":-0.012514469,
    "avg_value_ev":0.0813071908,
    "max_drawdown_pct":0.0,
    "stake_m":1.0,
    "min_edge":0.0,
    "investment_total_model":380.0,
    "acc":0.4868421053,
    "logloss":1.010250147,
    "brier":0.6025155162,
    "roi_bet365":-0.1271052632,
    "profit_bet365":-48.3,
    "investment_total":380.0,
    "n_bets_bet365":380,
    "stake_b":1.0,
    "investment_total_bet365":380.0,
    "delta_roi":0.0336052632,
    "delta_profit":12.77
  },
  {
    "model":"base",
    "test_season":2019,
    "train_until":2018,
    "n_bets_model":380,
    "roi_model":-0.0570789474,
    "profit_model":-21.69,
    "hit_rate":0.5026315789,
    "avg_odds":2.0283947368,
    "avg_edge":-0.0207710011,
    "avg_value_ev":0.1016729053,
    "max_drawdown_pct":7.6932153392,
    "stake_m":1.0,
    "min_edge":0.0,
    "investment_total_model":380.0,
    "acc":0.5105263158,
    "logloss":0.9839405174,
    "brier":0.5880212889,
    "roi_bet365":-0.0612894737,
    "profit_bet365":-23.29,
    "investment_total":380.0,
    "n_bets_bet365":380,
    "stake_b":1.0,
    "investment_total_bet365":380.0,
    "delta_roi":0.0042105263,
    "delta_profit":1.6
  },
  {
    "model":"base",
    "test_season":2020,
    "train_until":2019,
    "n_bets_model":380,
    "roi_model":0.0626578947,
    "profit_model":23.81,
    "hit_rate":0.5473684211,
    "avg_odds":2.0403157895,
    "avg_edge":-0.0017630991,
    "avg_value_ev":0.1048235431,
    "max_drawdown_pct":0.968798752,
    "stake_m":1.0,
    "min_edge":0.0,
    "investment_total_model":380.0,
    "acc":0.5315789474,
    "logloss":0.9878957925,
    "brier":0.5868265578,
    "roi_bet365":-0.0193684211,
    "profit_bet365":-7.36,
    "investment_total":380.0,
    "n_bets_bet365":380,
    "stake_b":1.0,
    "investment_total_bet365":380.0,
    "delta_roi":0.0820263158,
    "delta_profit":31.17
  },
  {
    "model":"base",
    "test_season":2021,
    "train_until":2020,
    "n_bets_model":380,
    "roi_model":0.0040263158,
    "profit_model":1.53,
    "hit_rate":0.5263157895,
    "avg_odds":2.0182894737,
    "avg_edge":-0.0129167009,
    "avg_value_ev":0.0810965004,
    "max_drawdown_pct":2.5151515152,
    "stake_m":1.0,
    "min_edge":0.0,
    "investment_total_model":380.0,
    "acc":0.5157894737,
    "logloss":0.9877620193,
    "brier":0.5885172709,
    "roi_bet365":-0.0451315789,
    "profit_bet365":-17.15,
    "investment_total":380.0,
    "n_bets_bet365":380,
    "stake_b":1.0,
    "investment_total_bet365":380.0,
    "delta_roi":0.0491578947,
    "delta_profit":18.68
  },
  {
    "model":"base",
    "test_season":2022,
    "train_until":2021,
    "n_bets_model":380,
    "roi_model":0.0382368421,
    "profit_model":14.53,
    "hit_rate":0.5447368421,
    "avg_odds":2.0046842105,
    "avg_edge":0.0051044734,
    "avg_value_ev":0.0660055477,
    "max_drawdown_pct":1.1889092017,
    "stake_m":1.0,
    "min_edge":0.0,
    "investment_total_model":380.0,
    "acc":0.5421052632,
    "logloss":0.9797455179,
    "brier":0.5830972207,
    "roi_bet365":0.0182368421,
    "profit_bet365":6.93,
    "investment_total":380.0,
    "n_bets_bet365":380,
    "stake_b":1.0,
    "investment_total_bet365":380.0,
    "delta_roi":0.02,
    "delta_profit":7.6
  },
  {
    "model":"base",
    "test_season":2023,
    "train_until":2022,
    "n_bets_model":380,
    "roi_model":0.0418157895,
    "profit_model":15.89,
    "hit_rate":0.5552631579,
    "avg_odds":1.982,
    "avg_edge":-0.0040182553,
    "avg_value_ev":0.0589225169,
    "max_drawdown_pct":0.9904502046,
    "stake_m":1.0,
    "min_edge":0.0,
    "investment_total_model":380.0,
    "acc":0.5526315789,
    "logloss":0.9473323353,
    "brier":0.5630388321,
    "roi_bet365":0.0217894737,
    "profit_bet365":8.28,
    "investment_total":380.0,
    "n_bets_bet365":380,
    "stake_b":1.0,
    "investment_total_bet365":380.0,
    "delta_roi":0.0200263158,
    "delta_profit":7.61
  },
  {
    "model":"base",
    "test_season":2024,
    "train_until":2023,
    "n_bets_model":380,
    "roi_model":0.0871052632,
    "profit_model":33.1,
    "hit_rate":0.5763157895,
    "avg_odds":1.9670526316,
    "avg_edge":-0.0078545657,
    "avg_value_ev":0.0837650351,
    "max_drawdown_pct":0.714334823,
    "stake_m":1.0,
    "min_edge":0.0,
    "investment_total_model":380.0,
    "acc":0.5447368421,
    "logloss":0.9534095113,
    "brier":0.5640414982,
    "roi_bet365":-0.018,
    "profit_bet365":-6.84,
    "investment_total":380.0,
    "n_bets_bet365":380,
    "stake_b":1.0,
    "investment_total_bet365":380.0,
    "delta_roi":0.1051052632,
    "delta_profit":39.94
  },
  {
    "model":"base",
    "test_season":2025,
    "train_until":2024,
    "n_bets_model":58,
    "roi_model":-0.25,
    "profit_model":-14.5,
    "hit_rate":0.4482758621,
    "avg_odds":2.0567241379,
    "avg_edge":-0.0062231771,
    "avg_value_ev":0.1558223718,
    "max_drawdown_pct":24.0,
    "stake_m":1.0,
    "min_edge":0.0,
    "investment_total_model":58.0,
    "acc":0.5344827586,
    "logloss":0.9469824231,
    "brier":0.5631663157,
    "roi_bet365":-0.0632758621,
    "profit_bet365":-3.67,
    "investment_total":58.0,
    "n_bets_bet365":58,
    "stake_b":1.0,
    "investment_total_bet365":58.0,
    "delta_roi":-0.1867241379,
    "delta_profit":-10.83
  }
]